sandstone_slurm
