Metadata-Version: 1.1
Name: sandstone-slurm-assist
Version: 0.11.0
Summary: Sandstone HPC - Slurm Assist App
Home-page: https://github.com/SandstoneHPC/sandstone-slurm-assist
Author: Zebula Sampedro
Author-email: sampedro@colorado.edu
License: MIT, see LICENSE
Platform: UNKNOWN
Classifier: Development Status :: 3 - Alpha
Classifier: Intended Audience :: Developers
Classifier: Natural Language :: English
Classifier: Operating System :: Unix
Classifier: Topic :: Software Development :: User Interfaces
Classifier: Topic :: Software Development :: Build Tools
Classifier: Topic :: Text Editors :: Integrated Development Environments (IDE)
Classifier: Topic :: Terminals :: Terminal Emulators/X Terminals
Classifier: License :: OSI Approved :: MIT License
Classifier: Programming Language :: Python :: 2.7
Classifier: Programming Language :: JavaScript
